<?xml version="1.0"?><metadata><idinfo><citation><citeinfo><origin>Minnesota Department of Natural Resources (MNDNR)</origin><pubdate>20090424</pubdate><title>MNDNR Administered State Forest Roads</title><mgmg1cid></mgmg1cid><pubinfo><publish>MNDNR - Division of Forestry</publish></pubinfo><onlink>http://gisdata.mn.gov/dataset/trans-state-forest-roads-wheels</onlink></citeinfo></citation><descript><abstract>Roads administered by the Commissioner of Natural Resources to provide access to lands administered by the Division of Forestry. These roads are generally open to the public for recreational use. Some of the segments in this shapefile are components of County administered forest road systems which cross State land. State Forest Roads are classified as either system roads or minimum maintenance roads. System roads are generally well maintained and capable of supporting low-clearance highway licensed vehicles. Minimum maintenance roads are not capable of sustaining routine traffic by highway licensed vehicles. They are posted with signs which state "Road may be impassable. Travel at your own risk".</abstract><purpose>To provide an inventory of the the State Forest Road system for  access to perform resource management activities and as a reference for recreational activities.</purpose><supplinf>There are 29 counties in Minnesota which contain at least one designated forest road segment.</supplinf></descript><timeperd><current>Time Period of Content Date indicates when dataset was last updated.  These data are pulled regularly from the DNR's WHEELS database and should be considered up-to-date.</current><timeinfo><sngdate><caldate>20140725</caldate></sngdate></timeinfo></timeperd><status><progress>Complete</progress><update>As needed</update></status><spdom><bounding><westbc>-95.593299</westbc><eastbc>-89.816454</eastbc><northbc>48.988422</northbc><southbc>43.588208</southbc></bounding></spdom><keywords><theme><themekey>transportation, Forest, Road, Transportation, Access, State, Facilities</themekey><themekt>ISO 19115 Category</themekt></theme><place><placekey>Minnesota, MN</placekey></place></keywords><accconst>None</accconst><useconst>Use of the data are constrained only by the DNR GIS Data License Agreement. See the Distribution Liability section below for a link.</useconst><native>ArcView Shapefile</native><browse><browsen>ftp://gdrs.dnr.state.mn.us/gdrs/data/pub/us_mn_state_dnr/trans_state_forest_roads_wheels/preview/preview.jpg</browsen></browse><ptcontac><cntinfo><cntperp><cntorg>Minnesota DNR - Division of Forestry</cntorg><cntper>John  Faulkner</cntper></cntperp><cntpos>Forest Roads Program Coordinator</cntpos><cntaddr><addrtype>Mailing and Physical</addrtype><address>DNR Forestry
6603 Bemidji Ave. N</address><city>Bemidji</city><state>MN</state><postal>56601</postal></cntaddr><cntvoice>218-308-2363</cntvoice><cntfax>21-755-4417</cntfax><cntemail>john.faulkner@state.mn.us</cntemail></cntinfo></ptcontac></idinfo><dataqual><logic>Data are topologically verified using ArcGIS 9.3.  All lines intersect where intended.</logic><complete>There are other routes on State forest lands which are not included as part of the forest road inventory because they are not open for motorized recreational uses by the public. </complete><posacc><horizpa><horizpar>Not specifically assessed
</horizpar></horizpa><vertacc><vertaccr>Not Applicable
</vertaccr></vertacc></posacc><lineage><srcinfo><srcscale>Source layer road_wtfrln3:  12000
</srcscale></srcinfo><procstep><procdesc>Derived from the WHEELS.TREADWAY feature class in the MNDNR's enterprise geodatabase.
</procdesc></procstep></lineage></dataqual><spdoinfo><indspref></indspref><direct>vector</direct><mgmg3obj>line</mgmg3obj><mgmg3til>state</mgmg3til></spdoinfo><spref><vertdef><altsys><altdatum>Not Applicable</altdatum><altunits>Not Applicable</altunits></altsys><depthsys><depthdn>Not Applicable</depthdn><depthdu>Not Applicable</depthdu></depthsys></vertdef><horizsys><planar><gridsys><gridsysn>Universal Transverse Mercator</gridsysn><utm><utmzone>15</utmzone></utm></gridsys><planci><plandu>meters</plandu></planci></planar><geodetic><horizdn>NAD83</horizdn><ellips>GRS80</ellips></geodetic></horizsys></spref><eainfo><detailed><enttyp><enttypl>dnr_state_forest_roads_wheels_database</enttypl><enttypd>Attribute table for DNR State Forest Roads - WHEELS Database</enttypd></enttyp><attr><attrlabl>TREADCLASS</attrlabl><attrdef>Treadway Class</attrdef><attrdomv><edom><edomv>1</edomv><edomvd>System Road</edomvd></edom></attrdomv><attrdomv><edom><edomv>2</edomv><edomvd>Minimum Maintenance Road</edomvd></edom></attrdomv></attr><attr><attrlabl>ROAD_NUM</attrlabl><attrdef>Road Number</attrdef></attr><attr><attrlabl>ROAD_NAME</attrlabl><attrdef>Road Name</attrdef></attr><attr><attrlabl>LEN_MILES</attrlabl><attrdef>Length of feature in miles, as calculated by the GIS</attrdef></attr></detailed></eainfo><distinfo><resdesc>trans_state_forest_roads_wheels</resdesc><distliab>The Minnesota Department of Natural Resources General Geographic Data License Agreement is online: http://www.dnr.state.mn.us/sitetools/data_software_license.html
</distliab><stdorder><digform><digtinfo><formname>ArcView Shapefile</formname><formvern>3.3</formvern><transize>1024</transize></digtinfo></digform><ordering>Please visit the download page for this dataset on the Minnesota Geospatial Commons website using the web link below (Online Linkage).</ordering></stdorder><distrib><cntinfo><cntperp><cntorg>Minnesota Department of Natural Resources</cntorg><cntper>Zeb Thomas</cntper></cntperp><cntpos>GIS Data Systems Coordinator</cntpos><cntaddr><addrtype>Mailing and Physical</addrtype><address>500 Lafayette Rd</address><city>St. Paul</city><state>MN</state><postal>55155-4011</postal></cntaddr><cntvoice>651-259-5637</cntvoice><cntemail>zeb.thomas@state.mn.us</cntemail></cntinfo></distrib></distinfo><metainfo><metd>20140725</metd><metstdn>Minnesota Geographic Metadata Guidelines</metstdn><metstdv>1.2</metstdv><metextns><onlink>http://www.mngeo.state.mn.us/committee/standards/mgmg/metadata.htm</onlink></metextns><metc><cntinfo><cntperp><cntorg>Minnesota Department of Natural Resources</cntorg><cntper>Zeb Thomas</cntper></cntperp><cntpos>GIS Data Systems Coordinator</cntpos><cntaddr><addrtype>Mailing and Physical</addrtype><address>500 Lafayette Rd</address><city>St. Paul</city><state>MN</state><postal>55155-4011</postal></cntaddr><cntvoice>651-259-5637</cntvoice><cntemail>zeb.thomas@state.mn.us</cntemail></cntinfo></metc></metainfo></metadata>